[{"iob":1.999,"activity":0.0075,"bolussnooze":0.345,"basaliob":-0.066,"netbasalinsulin":-0.1,"hightempinsulin":0.5,"time":"2016-05-24T03:40:30.000Z"},{"iob":1.902,"activity":0.0094,"bolussnooze":0.136,"basaliob":-0.103,"netbasalinsulin":-0.15,"hightempinsulin":0.5,"time":"2016-05-24T03:45:30.000Z"},{"iob":1.796,"activity":0.0113,"bolussnooze":0.022,"basaliob":-0.141,"netbasalinsulin":-0.25,"hightempinsulin":0.45,"time":"2016-05-24T03:50:30.000Z"},{"iob":1.68,"activity":0.0131,"bolussnooze":0,"basaliob":-0.18,"netbasalinsulin":-0.3,"hightempinsulin":0.45,"time":"2016-05-24T03:55:30.000Z"},{"iob":1.556,"activity":0.0149,"bolussnooze":0,"basaliob":-0.22,"netbasalinsulin":-0.4,"hightempinsulin":0.4,"time":"2016-05-24T04:00:30.000Z"},{"iob":1.422,"activity":0.0167,"bolussnooze":0,"basaliob":-0.26,"netbasalinsulin":-0.5,"hightempinsulin":0.35,"time":"2016-05-24T04:05:30.000Z"},{"iob":1.33,"activity":0.0185,"bolussnooze":0,"basaliob":-0.251,"netbasalinsulin":-0.5,"hightempinsulin":0.35,"time":"2016-05-24T04:10:30.000Z"},{"iob":1.228,"activity":0.0203,"bolussnooze":0,"basaliob":-0.243,"netbasalinsulin":-0.55,"hightempinsulin":0.3,"time":"2016-05-24T04:15:30.000Z"},{"iob":1.118,"activity":0.022,"bolussnooze":0,"basaliob":-0.235,"netbasalinsulin":-0.6,"hightempinsulin":0.25,"time":"2016-05-24T04:20:30.000Z"},{"iob":1.002,"activity":0.0232,"bolussnooze":0,"basaliob":-0.227,"netbasalinsulin":-0.6,"hightempinsulin":0.25,"time":"2016-05-24T04:25:30.000Z"},{"iob":0.892,"activity":0.0219,"bolussnooze":0,"basaliob":-0.218,"netbasalinsulin":-0.6,"hightempinsulin":0.25,"time":"2016-05-24T04:30:30.000Z"},{"iob":0.789,"activity":0.0206,"bolussnooze":0,"basaliob":-0.209,"netbasalinsulin":-0.6,"hightempinsulin":0.25,"time":"2016-05-24T04:35:30.000Z"},{"iob":0.693,"activity":0.0193,"bolussnooze":0,"basaliob":-0.199,"netbasalinsulin":-0.6,"hightempinsulin":0.25,"time":"2016-05-24T04:40:30.000Z"},{"iob":0.603,"activity":0.0179,"bolussnooze":0,"basaliob":-0.189,"netbasalinsulin":-0.6,"hightempinsulin":0.25,"time":"2016-05-24T04:45:30.000Z"},{"iob":0.52,"activity":0.0166,"bolussnooze":0,"basaliob":-0.178,"netbasalinsulin":-0.6,"hightempinsulin":0.25,"time":"2016-05-24T04:50:30.000Z"},{"iob":0.443,"activity":0.0154,"bolussnooze":0,"basaliob":-0.166,"netbasalinsulin":-0.5,"hightempinsulin":0.25,"time":"2016-05-24T04:55:30.000Z"},{"iob":0.373,"activity":0.0141,"bolussnooze":0,"basaliob":-0.155,"netbasalinsulin":-0.45,"hightempinsulin":0.25,"time":"2016-05-24T05:00:30.000Z"},{"iob":0.308,"activity":0.0129,"bolussnooze":0,"basaliob":-0.143,"netbasalinsulin":-0.4,"hightempinsulin":0.25,"time":"2016-05-24T05:05:30.000Z"},{"iob":0.249,"activity":0.0118,"bolussnooze":0,"basaliob":-0.132,"netbasalinsulin":-0.35,"hightempinsulin":0.25,"time":"2016-05-24T05:10:30.000Z"},{"iob":0.196,"activity":0.0107,"bolussnooze":0,"basaliob":-0.121,"netbasalinsulin":-0.25,"hightempinsulin":0.25,"time":"2016-05-24T05:15:30.000Z"},{"iob":0.148,"activity":0.0096,"bolussnooze":0,"basaliob":-0.11,"netbasalinsulin":-0.2,"hightempinsulin":0.25,"time":"2016-05-24T05:20:30.000Z"},{"iob":0.105,"activity":0.0085,"bolussnooze":0,"basaliob":-0.1,"netbasalinsulin":-0.15,"hightempinsulin":0.25,"time":"2016-05-24T05:25:30.000Z"},{"iob":0.068,"activity":0.0074,"bolussnooze":0,"basaliob":-0.091,"netbasalinsulin":-0.1,"hightempinsulin":0.25,"time":"2016-05-24T05:30:30.000Z"},{"iob":0.037,"activity":0.0062,"bolussnooze":0,"basaliob":-0.081,"netbasalinsulin":-0.1,"hightempinsulin":0.25,"time":"2016-05-24T05:35:30.000Z"},{"iob":0.012,"activity":0.0051,"bolussnooze":0,"basaliob":-0.072,"netbasalinsulin":-0.1,"hightempinsulin":0.25,"time":"2016-05-24T05:40:30.000Z"},{"iob":-0.008,"activity":0.004,"bolussnooze":0,"basaliob":-0.063,"netbasalinsulin":-0.1,"hightempinsulin":0.25,"time":"2016-05-24T05:45:30.000Z"},{"iob":-0.022,"activity":0.0028,"bolussnooze":0,"basaliob":-0.055,"netbasalinsulin":-0.1,"hightempinsulin":0.25,"time":"2016-05-24T05:50:30.000Z"},{"iob":-0.031,"activity":0.0017,"bolussnooze":0,"basaliob":-0.046,"netbasalinsulin":-0.1,"hightempinsulin":0.25,"time":"2016-05-24T05:55:30.000Z"},{"iob":-0.034,"activity":0.0006,"bolussnooze":0,"basaliob":-0.038,"netbasalinsulin":-0.15,"hightempinsulin":0.2,"time":"2016-05-24T06:00:30.000Z"},{"iob":-0.031,"activity":-0.0005,"bolussnooze":0,"basaliob":-0.031,"netbasalinsulin":-0.2,"hightempinsulin":0.15,"time":"2016-05-24T06:05:30.000Z"},{"iob":-0.024,"activity":-0.0014,"bolussnooze":0,"basaliob":-0.024,"netbasalinsulin":-0.3,"hightempinsulin":0.05,"time":"2016-05-24T06:10:30.000Z"},{"iob":-0.018,"activity":-0.0012,"bolussnooze":0,"basaliob":-0.018,"netbasalinsulin":-0.35,"hightempinsulin":0,"time":"2016-05-24T06:15:30.000Z"},{"iob":-0.013,"activity":-0.001,"bolussnooze":0,"basaliob":-0.013,"netbasalinsulin":-0.35,"hightempinsulin":0,"time":"2016-05-24T06:20:30.000Z"},{"iob":-0.009,"activity":-0.0008,"bolussnooze":0,"basaliob":-0.009,"netbasalinsulin":-0.35,"hightempinsulin":0,"time":"2016-05-24T06:25:30.000Z"},{"iob":-0.005,"activity":-0.0006,"bolussnooze":0,"basaliob":-0.005,"netbasalinsulin":-0.35,"hightempinsulin":0,"time":"2016-05-24T06:30:30.000Z"},{"iob":-0.003,"activity":-0.0005,"bolussnooze":0,"basaliob":-0.003,"netbasalinsulin":-0.3,"hightempinsulin":0,"time":"2016-05-24T06:35:30.000Z"}]
