{
  "bg": 119, 
  "temp": "absolute", 
  "snoozeBG": 119, 
  "recieved": true, 
  "predBGs": {
    "aCOB": [
      119, 
      126, 
      131, 
      134, 
      137, 
      138, 
      138, 
      137, 
      137, 
      137, 
      137, 
      137, 
      137, 
      138, 
      138, 
      139, 
      140, 
      142, 
      143, 
      144, 
      146, 
      147, 
      148, 
      149, 
      150, 
      151, 
      152, 
      152, 
      153, 
      153, 
      154, 
      154, 
      155
    ], 
    "IOB": [
      119, 
      117, 
      115, 
      114, 
      112, 
      111, 
      110, 
      110, 
      109, 
      109, 
      109, 
      109, 
      110, 
      110, 
      111, 
      112, 
      113, 
      114, 
      116, 
      117, 
      118, 
      119, 
      121, 
      122, 
      123, 
      124, 
      124, 
      125, 
      126, 
      126, 
      127, 
      127, 
      127, 
      127, 
      128
    ]
  }, 
  "rate": 0.0, 
  "reason": "COB: 9, Dev: 0, BGI: -1.93, Target: 140; Eventual BG 119<140, setting -0.616U/hr", 
  "eventualBG": 119, 
  "timestamp": "2016-05-10T16:54:16.339573", 
  "duration": 30, 
  "tick": -2
}