{
  "device": "openaps://indy-e2", 
  "pump": {
    "battery": {
      "status": "normal", 
      "voltage": 1.54
    }, 
    "status": {
      "status": "normal", 
      "timestamp": "2016-04-27T21:19:47.000Z", 
      "bolusing": false, 
      "suspended": false
    }, 
    "reservoir": 144.525, 
    "clock": "2016-04-27T14:18:52-07:00"
  }, 
  "openaps": {
    "suggested": {
      "bg": 153, 
      "temp": "absolute", 
      "snoozeBG": 91, 
      "timestamp": "2016-04-27T21:21:04.000Z", 
      "predBGs": {
        "IOB": [
          153, 
          154, 
          155, 
          155, 
          154, 
          152, 
          149, 
          144, 
          139, 
          133, 
          126, 
          119, 
          112, 
          106, 
          99, 
          93, 
          88, 
          83, 
          78, 
          74, 
          70, 
          67, 
          64, 
          61, 
          59, 
          58, 
          57, 
          56, 
          55
        ]
      }, 
      "reason": "COB: 0, Dev: 47, BGI: -5.85, Target: 115; Eventual BG 64<110, but Avg. Delta 2.00 > Exp. Delta -3, temp 0.575 ~ req 0.6U/hr", 
      "eventualBG": 64, 
      "tick": "+2"
    }, 
    "iob": [
      {
        "netbasalinsulin": 0.75, 
        "activity": 0.0174, 
        "basaliob": 0.558, 
        "time": "2016-04-27T21:18:52.000Z", 
        "hightempinsulin": 1.5, 
        "bolussnooze": 0.266, 
        "iob": 2.029
      }, 
      {
        "netbasalinsulin": 0.6, 
        "activity": 0.0178, 
        "basaliob": 0.55, 
        "time": "2016-04-27T21:23:52.000Z", 
        "hightempinsulin": 1.35, 
        "bolussnooze": 0.158, 
        "iob": 1.941
      }, 
      {
        "netbasalinsulin": 0.5, 
        "activity": 0.0182, 
        "basaliob": 0.539, 
        "time": "2016-04-27T21:28:52.000Z", 
        "hightempinsulin": 1.25, 
        "bolussnooze": 0.08, 
        "iob": 1.85
      }, 
      {
        "netbasalinsulin": 0.4, 
        "activity": 0.0189, 
        "basaliob": 0.523, 
        "time": "2016-04-27T21:33:52.000Z", 
        "hightempinsulin": 1.15, 
        "bolussnooze": 0.029, 
        "iob": 1.755
      }, 
      {
        "netbasalinsulin": 0.35, 
        "activity": 0.0203, 
        "basaliob": 0.503, 
        "time": "2016-04-27T21:38:52.000Z", 
        "hightempinsulin": 1.1, 
        "bolussnooze": 0.006, 
        "iob": 1.654
      }, 
      {
        "netbasalinsulin": 0.25, 
        "activity": 0.0217, 
        "basaliob": 0.479, 
        "time": "2016-04-27T21:43:52.000Z", 
        "hightempinsulin": 1, 
        "bolussnooze": 0, 
        "iob": 1.545
      }, 
      {
        "netbasalinsulin": 0.2, 
        "activity": 0.023, 
        "basaliob": 0.452, 
        "time": "2016-04-27T21:48:52.000Z", 
        "hightempinsulin": 0.95, 
        "bolussnooze": 0, 
        "iob": 1.43
      }, 
      {
        "netbasalinsulin": 0.25, 
        "activity": 0.0239, 
        "basaliob": 0.422, 
        "time": "2016-04-27T21:53:52.000Z", 
        "hightempinsulin": 0.95, 
        "bolussnooze": 0, 
        "iob": 1.31
      }, 
      {
        "netbasalinsulin": 0.25, 
        "activity": 0.024, 
        "basaliob": 0.39, 
        "time": "2016-04-27T21:58:52.000Z", 
        "hightempinsulin": 0.95, 
        "bolussnooze": 0, 
        "iob": 1.19
      }, 
      {
        "netbasalinsulin": 0.3, 
        "activity": 0.0234, 
        "basaliob": 0.357, 
        "time": "2016-04-27T22:03:52.000Z", 
        "hightempinsulin": 0.95, 
        "bolussnooze": 0, 
        "iob": 1.073
      }, 
      {
        "netbasalinsulin": 0.35, 
        "activity": 0.0224, 
        "basaliob": 0.324, 
        "time": "2016-04-27T22:08:52.000Z", 
        "hightempinsulin": 0.95, 
        "bolussnooze": 0, 
        "iob": 0.961
      }, 
      {
        "netbasalinsulin": 0.4, 
        "activity": 0.0213, 
        "basaliob": 0.292, 
        "time": "2016-04-27T22:13:52.000Z", 
        "hightempinsulin": 0.95, 
        "bolussnooze": 0, 
        "iob": 0.854
      }, 
      {
        "netbasalinsulin": 0.4, 
        "activity": 0.02, 
        "basaliob": 0.262, 
        "time": "2016-04-27T22:18:52.000Z", 
        "hightempinsulin": 0.95, 
        "bolussnooze": 0, 
        "iob": 0.754
      }, 
      {
        "netbasalinsulin": 0.45, 
        "activity": 0.0188, 
        "basaliob": 0.233, 
        "time": "2016-04-27T22:23:52.000Z", 
        "hightempinsulin": 0.95, 
        "bolussnooze": 0, 
        "iob": 0.66
      }, 
      {
        "netbasalinsulin": 0.5, 
        "activity": 0.0176, 
        "basaliob": 0.205, 
        "time": "2016-04-27T22:28:52.000Z", 
        "hightempinsulin": 0.95, 
        "bolussnooze": 0, 
        "iob": 0.572
      }, 
      {
        "netbasalinsulin": 0.55, 
        "activity": 0.0165, 
        "basaliob": 0.178, 
        "time": "2016-04-27T22:33:52.000Z", 
        "hightempinsulin": 0.95, 
        "bolussnooze": 0, 
        "iob": 0.49
      }, 
      {
        "netbasalinsulin": 0.6, 
        "activity": 0.0152, 
        "basaliob": 0.153, 
        "time": "2016-04-27T22:38:52.000Z", 
        "hightempinsulin": 0.95, 
        "bolussnooze": 0, 
        "iob": 0.414
      }, 
      {
        "netbasalinsulin": 0.65, 
        "activity": 0.0139, 
        "basaliob": 0.129, 
        "time": "2016-04-27T22:43:52.000Z", 
        "hightempinsulin": 0.95, 
        "bolussnooze": 0, 
        "iob": 0.344
      }, 
      {
        "netbasalinsulin": 0.7, 
        "activity": 0.0126, 
        "basaliob": 0.107, 
        "time": "2016-04-27T22:48:52.000Z", 
        "hightempinsulin": 0.95, 
        "bolussnooze": 0, 
        "iob": 0.281
      }, 
      {
        "netbasalinsulin": 0.75, 
        "activity": 0.0113, 
        "basaliob": 0.087, 
        "time": "2016-04-27T22:53:52.000Z", 
        "hightempinsulin": 0.95, 
        "bolussnooze": 0, 
        "iob": 0.224
      }, 
      {
        "netbasalinsulin": 0.8, 
        "activity": 0.01, 
        "basaliob": 0.069, 
        "time": "2016-04-27T22:58:52.000Z", 
        "hightempinsulin": 0.95, 
        "bolussnooze": 0, 
        "iob": 0.174
      }, 
      {
        "netbasalinsulin": 0.85, 
        "activity": 0.0086, 
        "basaliob": 0.053, 
        "time": "2016-04-27T23:03:52.000Z", 
        "hightempinsulin": 0.95, 
        "bolussnooze": 0, 
        "iob": 0.132
      }, 
      {
        "netbasalinsulin": 0.85, 
        "activity": 0.0072, 
        "basaliob": 0.039, 
        "time": "2016-04-27T23:08:52.000Z", 
        "hightempinsulin": 0.95, 
        "bolussnooze": 0, 
        "iob": 0.096
      }, 
      {
        "netbasalinsulin": 0.85, 
        "activity": 0.0058, 
        "basaliob": 0.028, 
        "time": "2016-04-27T23:13:52.000Z", 
        "hightempinsulin": 0.95, 
        "bolussnooze": 0, 
        "iob": 0.067
      }, 
      {
        "netbasalinsulin": 0.85, 
        "activity": 0.0047, 
        "basaliob": 0.019, 
        "time": "2016-04-27T23:18:52.000Z", 
        "hightempinsulin": 0.95, 
        "bolussnooze": 0, 
        "iob": 0.044
      }, 
      {
        "netbasalinsulin": 0.85, 
        "activity": 0.0036, 
        "basaliob": 0.012, 
        "time": "2016-04-27T23:23:52.000Z", 
        "hightempinsulin": 0.95, 
        "bolussnooze": 0, 
        "iob": 0.026
      }, 
      {
        "netbasalinsulin": 0.7, 
        "activity": 0.0025, 
        "basaliob": 0.007, 
        "time": "2016-04-27T23:28:52.000Z", 
        "hightempinsulin": 0.8, 
        "bolussnooze": 0, 
        "iob": 0.013
      }, 
      {
        "netbasalinsulin": 0.55, 
        "activity": 0.0016, 
        "basaliob": 0.003, 
        "time": "2016-04-27T23:33:52.000Z", 
        "hightempinsulin": 0.65, 
        "bolussnooze": 0, 
        "iob": 0.005
      }, 
      {
        "netbasalinsulin": 0.45, 
        "activity": 0.0007, 
        "basaliob": 0.002, 
        "time": "2016-04-27T23:38:52.000Z", 
        "hightempinsulin": 0.55, 
        "bolussnooze": 0, 
        "iob": 0.002
      }, 
      {
        "netbasalinsulin": 0.3, 
        "activity": 0.0002, 
        "basaliob": 0.001, 
        "time": "2016-04-27T23:43:52.000Z", 
        "hightempinsulin": 0.4, 
        "bolussnooze": 0, 
        "iob": 0.001
      }, 
      {
        "netbasalinsulin": 0.2, 
        "activity": 0.0001, 
        "basaliob": 0, 
        "time": "2016-04-27T23:48:52.000Z", 
        "hightempinsulin": 0.3, 
        "bolussnooze": 0, 
        "iob": 0
      }, 
      {
        "netbasalinsulin": 0.05, 
        "activity": 0, 
        "basaliob": 0, 
        "time": "2016-04-27T23:53:52.000Z", 
        "hightempinsulin": 0.15, 
        "bolussnooze": 0, 
        "iob": 0
      }, 
      {
        "netbasalinsulin": -0.05, 
        "activity": 0, 
        "basaliob": 0, 
        "time": "2016-04-27T23:58:52.000Z", 
        "hightempinsulin": 0.05, 
        "bolussnooze": 0, 
        "iob": 0
      }, 
      {
        "netbasalinsulin": -0.05, 
        "activity": 0, 
        "basaliob": 0, 
        "time": "2016-04-28T00:03:52.000Z", 
        "hightempinsulin": 0.05, 
        "bolussnooze": 0, 
        "iob": 0
      }, 
      {
        "netbasalinsulin": 0, 
        "activity": 0, 
        "basaliob": 0, 
        "time": "2016-04-28T00:08:52.000Z", 
        "hightempinsulin": 0.05, 
        "bolussnooze": 0, 
        "iob": 0
      }, 
      {
        "netbasalinsulin": 0.05, 
        "activity": 0, 
        "basaliob": 0, 
        "time": "2016-04-28T00:13:52.000Z", 
        "hightempinsulin": 0.05, 
        "bolussnooze": 0, 
        "iob": 0
      }
    ], 
    "enacted": {
      "bg": 151, 
      "temp": "absolute", 
      "snoozeBG": 95, 
      "recieved": true, 
      "predBGs": {
        "IOB": [
          151, 
          153, 
          153, 
          153, 
          152, 
          151, 
          148, 
          144, 
          139, 
          133, 
          127, 
          120, 
          113, 
          107, 
          101, 
          96, 
          91, 
          86, 
          82, 
          78, 
          75, 
          72, 
          69, 
          67, 
          66, 
          65, 
          64, 
          63, 
          63, 
          63, 
          63, 
          63, 
          63, 
          63, 
          64
        ]
      }, 
      "reason": "COB: 0, Dev: 47, BGI: -5.81, Target: 115; Eventual BG 63<110, but Delta +4 > Exp. Delta -2.9; setting current basal of 0.6 as temp", 
      "rate": 0.575, 
      "eventualBG": 63, 
      "timestamp": "2016-04-27T21:18:45.000Z", 
      "duration": 30, 
      "tick": "+4"
    }
  }, 
  "mmtune": {
    "scanDetails": [
      [
        "916.500", 
        4, 
        -94
      ], 
      [
        "916.520", 
        3, 
        -95
      ], 
      [
        "916.540", 
        1, 
        -97
      ], 
      [
        "916.560", 
        3, 
        -90
      ], 
      [
        "916.580", 
        5, 
        -79
      ], 
      [
        "916.600", 
        4, 
        -82
      ], 
      [
        "916.620", 
        4, 
        -82
      ], 
      [
        "916.640", 
        5, 
        -77
      ], 
      [
        "916.660", 
        5, 
        -78
      ], 
      [
        "916.680", 
        5, 
        -79
      ], 
      [
        "916.700", 
        5, 
        -84
      ], 
      [
        "916.740", 
        2, 
        -96
      ], 
      [
        "916.780", 
        1, 
        -98
      ], 
      [
        "916.800", 
        2, 
        -96
      ], 
      [
        "916.820", 
        5, 
        -91
      ], 
      [
        "916.840", 
        5, 
        -92
      ], 
      [
        "916.860", 
        4, 
        -93
      ], 
      [
        "916.880", 
        5, 
        -91
      ], 
      [
        "916.900", 
        5, 
        -91
      ]
    ], 
    "setFreq": 916.64, 
    "timestamp": "2016-04-27T21:19:18.000Z", 
    "usedDefault": false
  }
}